{
  "minecraft:recipes/brewing/fermented_spider_eye": {
    "criteria": {
      "has_spider_eye": "2020-02-26 18:01:02 +0000"
    },
    "done": true
  },
  "minecraft:recipes/misc/charcoal": {
    "criteria": {
      "has_log": "2020-02-26 18:04:48 +0000"
    },
    "done": true
  },
  "minecraft:recipes/building_blocks/oak_planks": {
    "criteria": {
      "has_log": "2020-02-26 18:04:48 +0000"
    },
    "done": true
  },
  "minecraft:husbandry/balanced_diet": {
    "criteria": {
      "bread": "2020-02-26 18:13:18 +0000"
    },
    "done": false
  },
  "minecraft:husbandry/root": {
    "criteria": {
      "consumed_item": "2020-02-26 18:13:18 +0000"
    },
    "done": true
  },
  "minecraft:adventure/root": {
    "criteria": {
      "killed_something": "2020-02-26 18:00:57 +0000"
    },
    "done": true
  },
  "minecraft:adventure/kill_a_mob": {
    "criteria": {
      "minecraft:spider": "2020-02-26 18:00:57 +0000"
    },
    "done": true
  },
  "minecraft:adventure/kill_all_mobs": {
    "criteria": {
      "minecraft:spider": "2020-02-26 18:00:57 +0000"
    },
    "done": false
  },
  "minecraft:recipes/building_blocks/oak_wood": {
    "criteria": {
      "has_log": "2020-02-26 18:04:48 +0000"
    },
    "done": true
  },
  "minecraft:adventure/adventuring_time": {
    "criteria": {
      "minecraft:forest": "2020-02-26 18:04:24 +0000",
      "minecraft:beach": "2020-02-26 18:02:29 +0000",
      "minecraft:wooded_hills": "2020-02-26 18:00:18 +0000",
      "minecraft:plains": "2020-02-26 18:00:29 +0000"
    },
    "done": false
  },
  "DataVersion": 2230
}